cmdtrix/__init__.py
cmdtrix/__main__.py
cmdtrix/cmdtrix.py
cmdtrix/requirements.txt
cmdtrix/util/ArgsHandler.py
cmdtrix/util/Chars.py
cmdtrix/util/EventTimer.py
cmdtrix/util/__init__.py
cmdtrix/web/UpdateChecker.py
cmdtrix/web/__init__.py
cmdtrix-0.1.9.dist-info/entry_points.txt
cmdtrix-0.1.9.dist-info/LICENSE
cmdtrix-0.1.9.dist-info/WHEEL
cmdtrix-0.1.9.dist-info/METADATA
cmdtrix-0.1.9.dist-info/RECORD
