Metadata-Version: 2.1
Name: cmdtrix
Version: 0.1.9
Summary: Matrix-console-effect made in Python.
Keywords: console,crossplatform,matrix,python,terminal
Author-email: "Silas A. Kraume" <silas.kraume1552@gmail.com>
Requires-Python: >=3.7
Classifier: License :: OSI Approved :: MIT License
Classifier: Programming Language :: Python :: 3
Classifier: Programming Language :: Python :: 3.7
Classifier: Programming Language :: Python :: 3.8
Classifier: Programming Language :: Python :: 3.9
Classifier: Programming Language :: Python :: 3.10
Classifier: Programming Language :: Python :: 3.11
Classifier: Environment :: Console
Classifier: Operating System :: OS Independent
Classifier: Topic :: Terminals
Requires-Dist: colorama>=0.4.6; platform_system=='Windows'
Requires-Dist: pynput>=1.6.0
Project-URL: Download, https://github.com/SilenZcience/cmdtrix/tarball/master
Project-URL: Github, https://github.com/SilenZcience/cmdtrix
Project-URL: Tracker, https://github.com/SilenZcience/cmdtrix/issues
